Metadata-Version: 2.1
Name: rotary-embedding-tensorflow
Version: 0.1.1
Summary: Rotary Embedding - Tensorflow
Home-page: https://github.com/AryaAftab/rotary-embedding-tensorflow
Author: Arya Aftab
Author-email: arya.aftab@gmail.com
License: MIT
Keywords: deep learning,tensorflow,positional embedding
Platform: UNKNOWN
Classifier: Development Status :: 4 - Beta
Classifier: Intended Audience :: Developers
Classifier: Topic :: Scientific/Engineering :: Artificial Intelligence
Classifier: License :: OSI Approved :: MIT License
Classifier: Programming Language :: Python :: 3.6
License-File: LICENSE
